gromacs_py/__init__.py
gromacs_py/free_ener.py
gromacs_py/gmx/__init__.py
gromacs_py/gmx/gmxsys.py
gromacs_py/gmx/itp.py
gromacs_py/gmx/rtp.py
gromacs_py/gmx/topmol.py
gromacs_py/gmx/topsys.py
gromacs_py/gmx/template/equi.mdp
gromacs_py/gmx/template/equi_charmm36.mdp
gromacs_py/gmx/template/equi_charmm36_bilayer.mdp
gromacs_py/gmx/template/equi_implicit_sol.mdp
gromacs_py/gmx/template/equi_vsites.mdp
gromacs_py/gmx/template/martini_v2.x_new-rf.mdp
gromacs_py/gmx/template/mini.mdp
gromacs_py/gmx/template/charmm36-jul2017.ff/atomtypes.atp
gromacs_py/gmx/template/charmm36-jul2017.ff/cmap.itp
gromacs_py/gmx/template/charmm36-jul2017.ff/ffbonded.itp
gromacs_py/gmx/template/charmm36-jul2017.ff/ffnonbonded.itp
gromacs_py/gmx/template/charmm36-jul2017.ff/forcefield.doc
gromacs_py/gmx/template/charmm36-jul2017.ff/forcefield.itp
gromacs_py/gmx/template/charmm36-jul2017.ff/gb.itp
gromacs_py/gmx/template/charmm36-jul2017.ff/ions.itp
gromacs_py/gmx/template/charmm36-jul2017.ff/merged.arn
gromacs_py/gmx/template/charmm36-jul2017.ff/merged.c.tdb
gromacs_py/gmx/template/charmm36-jul2017.ff/merged.hdb
gromacs_py/gmx/template/charmm36-jul2017.ff/merged.n.tdb
gromacs_py/gmx/template/charmm36-jul2017.ff/merged.r2b
gromacs_py/gmx/template/charmm36-jul2017.ff/merged.rtp
gromacs_py/gmx/template/charmm36-jul2017.ff/merged.vsd
gromacs_py/gmx/template/charmm36-jul2017.ff/nbfix.itp
gromacs_py/gmx/template/charmm36-jul2017.ff/old_c36_cmap.itp
gromacs_py/gmx/template/charmm36-jul2017.ff/spc.itp
gromacs_py/gmx/template/charmm36-jul2017.ff/spce.itp
gromacs_py/gmx/template/charmm36-jul2017.ff/tip3p.itp
gromacs_py/gmx/template/charmm36-jul2017.ff/tip4p.itp
gromacs_py/gmx/template/charmm36-jul2017.ff/watermodels.dat
gromacs_py/gmx/template/octanol/OCO_GMX.itp
gromacs_py/gmx/template/octanol/OCO_GMX_atomtypes.itp
gromacs_py/gmx/template/octanol/prod_OCO.gro
gromacs_py/test/__init__.py
gromacs_py/test/datafiles.py
gromacs_py/test/test_FreeEner.py
gromacs_py/test/test_GmxSys.py
gromacs_py-2.0.3.dist-info/LICENSE
gromacs_py-2.0.3.dist-info/METADATA
gromacs_py-2.0.3.dist-info/WHEEL
gromacs_py-2.0.3.dist-info/top_level.txt
gromacs_py-2.0.3.dist-info/RECORD
