Metadata-Version: 2.1
Name: gromacs-py
Version: 2.0.3
Summary: Gromacs_py is a python library allowing a simplified use of the gromacs MD simulation software.
Home-page: https://github.com/samuelmurail/gromacs_py
Author: Samuel Murail
Author-email: samuel.murail@u-paris.fr
License: UNKNOWN
Project-URL: Bug Reports, https://github.com/samuelmurail/gromacs_py/issues
Project-URL: Funding, https://www.impots.gouv.fr/portail/
Project-URL: Source, https://github.com/samuelmurail/gromacs_py
Platform: UNKNOWN
Classifier: Development Status :: 5 - Production/Stable
Classifier: License :: OSI Approved :: GNU General Public License v2 (GPLv2)
Classifier: Natural Language :: English
Classifier: Operating System :: OS Independent
Classifier: Programming Language :: Python :: 3
Classifier: Programming Language :: Python :: 3.8
Classifier: Programming Language :: Python :: 3.7
Classifier: Programming Language :: Python :: 3.6
Classifier: Programming Language :: Python :: 3.5
Classifier: Topic :: Scientific/Engineering :: Bio-Informatics
Requires-Python: >=3.5
License-File: LICENSE
Requires-Dist: pandas
Requires-Dist: matplotlib
Requires-Dist: os-command-py (==1.1.0)
Requires-Dist: pdb-manip-py (==1.4.2)
Requires-Dist: tqdm
